benmillerscripts/FFTArrayAnalysis.py
benmillerscripts/FileDialogs.py
benmillerscripts/ISDatasetProcessing.py
BenMillerScripts-0.1.7.dist-info/LICENSE
BenMillerScripts-0.1.7.dist-info/METADATA
BenMillerScripts-0.1.7.dist-info/WHEEL
BenMillerScripts-0.1.7.dist-info/top_level.txt
BenMillerScripts-0.1.7.dist-info/RECORD
