Metadata-Version: 2.1
Name: BenMillerScripts
Version: 0.1.7
Summary: Modules for Running Python scripts by Ben Miller in DigitalMicrograph
Home-page: https://www.gatan.com/resources/python-scripts
Author: Ben Miller
Author-email: benmiller002@aol.com
License: MIT
Requires-Python: >=3.7
License-File: LICENSE
Requires-Dist: scikit-learn
Requires-Dist: matplotlib
Requires-Dist: numpy
Requires-Dist: scipy
Requires-Dist: scikit-image
Requires-Dist: pandas
Requires-Dist: tqdm
